humanize_ai/__init__.py
humanize_ai/python_humanize_ai/__init__.py
humanize_ai/python_humanize_ai/humanize_string.py
humanize_ai-1.1.0.dist-info/licenses/LICENSE
humanize_ai-1.1.0.dist-info/METADATA
humanize_ai-1.1.0.dist-info/WHEEL
humanize_ai-1.1.0.dist-info/entry_points.txt
humanize_ai-1.1.0.dist-info/top_level.txt
humanize_ai-1.1.0.dist-info/RECORD
